Casabourselib/Casabourselib.py
Casabourselib/__init__.py
Casabourselib-2.0.1.dist-info/METADATA
Casabourselib-2.0.1.dist-info/WHEEL
Casabourselib-2.0.1.dist-info/top_level.txt
Casabourselib-2.0.1.dist-info/RECORD
