Metadata-Version: 2.1
Name: Casabourselib
Version: 2.0.1
Summary: Like yfinance but for Moroccan stocks
Home-page: UNKNOWN
Author: Yassine Rhzif & Ahmed Ouaboune
Author-email: Rhzif@hotmail.com
License: UNKNOWN
Keywords: python,Bourse de casa,stocks,actions,actions maroc
Platform: UNKNOWN
Classifier: Development Status :: 1 - Planning
Classifier: Intended Audience :: Developers
Classifier: Programming Language :: Python :: 3
Classifier: Operating System :: Unix
Classifier: Operating System :: MacOS :: MacOS X
Classifier: Operating System :: Microsoft :: Windows
Requires-Dist: requests
Requires-Dist: pandas
Requires-Dist: bs4
Requires-Dist: investpy
